{"stats":{"minecraft:custom":{"minecraft:time_since_rest":10838,"minecraft:crouch_one_cm":2407,"minecraft:play_time":49613,"minecraft:sprint_one_cm":46435,"minecraft:damage_taken":962,"minecraft:deaths":6,"minecraft:walk_one_cm":98745,"minecraft:sneak_time":2401,"minecraft:walk_under_water_one_cm":3529,"minecraft:mob_kills":2,"minecraft:drop":4,"minecraft:aviate_one_cm":38805,"minecraft:jump":93,"minecraft:leave_game":1,"minecraft:time_since_death":10565,"minecraft:walk_on_water_one_cm":1010,"minecraft:climb_one_cm":720,"minecraft:total_world_time":49613,"minecraft:fall_one_cm":418,"minecraft:fly_one_cm":465748},"minecraft:picked_up":{"minecraft:sculk_catalyst":1,"apotheosis:warden_tendril":1,"minecraft:sand":4,"minecraft:lily_pad":3,"icarus:zanzas_wings":1,"minecraft:oak_button":1,"minecraft:redstone":27,"minecraft:sugar_cane":1},"minecraft:dropped":{"create:handheld_worldshaper":2,"icarus:zanzas_wings":1,"minecraft:firework_rocket":1},"minecraft:killed_by":{"minecraft:player":3},"minecraft:killed":{"mutantmonsters:creeper_minion":2},"minecraft:used":{"minecraft:warden_spawn_egg":1,"create:handheld_worldshaper":4,"minecraft:water_bucket":1,"minecraft:sand":108,"immersive_aircraft:airship":1,"minecraft:armor_stand":3,"minecraft:grass_block":17,"minecraft:string":2,"minecraft:redstone":1,"minecraft:oak_button":1,"immersive_aircraft:biplane":4,"minecraft:stone":8,"immersive_aircraft:warship":1,"minecraft:sugar_cane":2}},"DataVersion":3465}